setup.py
cloudify_script_plugin.egg-info/PKG-INFO
cloudify_script_plugin.egg-info/SOURCES.txt
cloudify_script_plugin.egg-info/dependency_links.txt
cloudify_script_plugin.egg-info/requires.txt
cloudify_script_plugin.egg-info/top_level.txt
script_runner/__init__.py
script_runner/constants.py
script_runner/eval_env.py
script_runner/tasks.py