Metadata-Version: 1.0
Name: cloudify-script-plugin
Version: 1.5.3
Summary: Plugin for running scripts
Home-page: UNKNOWN
Author: Cloudify
Author-email: hello@cloudify.co
License: LICENSE
Platform: UNKNOWN
